cursofiap/__init__.py
cursofiap/core.py
cursofiap_bruna_test-1.0.0.dist-info/METADATA
cursofiap_bruna_test-1.0.0.dist-info/WHEEL
cursofiap_bruna_test-1.0.0.dist-info/top_level.txt
cursofiap_bruna_test-1.0.0.dist-info/RECORD
