Metadata-Version: 2.4
Name: cursofiap-bruna-test
Version: 1.0.0
Summary: Descricao da sua lib cursofiap
Home-page: https://github.com/tadrianonet/cursofiap
Author: Bruna F Ballerini
Author-email: brunaballerini@gmail.com
License: MIT
Dynamic: author
Dynamic: author-email
Dynamic: description
Dynamic: description-content-type
Dynamic: home-page
Dynamic: license
Dynamic: summary
